prettytimer.py
prettytimer-0.1.dev5.dist-info/METADATA
prettytimer-0.1.dev5.dist-info/WHEEL
prettytimer-0.1.dev5.dist-info/top_level.txt
prettytimer-0.1.dev5.dist-info/RECORD
