Metadata-Version: 2.1
Name: prettytimer
Version: 0.1.dev5
Summary: a sssuper simple yet useful tool for you to collct     the running time of the codeblock
Home-page: https://github.com/kinredon/prettytimer
Author: kinredon
Author-email: kinredon@163.com
Maintainer: kinredon
License: BSD (3 clause)
Project-URL: Source, https://github.com/kinredon/prettytimer
Platform: UNKNOWN
Classifier: Programming Language :: Python
Classifier: Programming Language :: Python :: 2
Classifier: Programming Language :: Python :: 2.7
Classifier: Programming Language :: Python :: 3
Classifier: Programming Language :: Python :: 3.5
Classifier: Programming Language :: Python :: 3.6
Classifier: Programming Language :: Python :: 3.7
Classifier: Programming Language :: Python :: 3.8
Classifier: License :: OSI Approved :: BSD License
Classifier: Topic :: Text Processing
Requires-Python: >=2.7, !=3.0.*, !=3.1.*, !=3.2.*, !=3.3.*, !=3.4.*
